coshell/__init__.py
coshell/internal/__init__.py
coshell/internal/chat.py
coshell/internal/cli.py
coshell/internal/openai/__init__.py
coshell/internal/openai/api.py
coshell/internal/openai/chat_completions.py
coshell/internal/openai/endpoint.py
coshell/main.py
coshell-0.1.1.dist-info/entry_points.txt
coshell-0.1.1.dist-info/WHEEL
coshell-0.1.1.dist-info/METADATA
coshell-0.1.1.dist-info/RECORD
